niteru/__init__.py
niteru/dataclasses.py
niteru/html_parser.py
niteru/similarity.py
niteru/structural_similarity.py
niteru/style_similarity.py
niteru/utils.py
niteru-0.2.1.dist-info/LICENSE
niteru-0.2.1.dist-info/WHEEL
niteru-0.2.1.dist-info/METADATA
niteru-0.2.1.dist-info/RECORD
