Metadata-Version: 2.1
Name: niteru
Version: 0.2.1
Summary: A set of similarity metrics to compare html files
Home-page: https://github.com/ninoseki/niteru
Author: Manabu Niseki
Author-email: manabu.niseki@gmail.com
Requires-Python: >=3.7,<4.0
Classifier: Programming Language :: Python :: 3
Classifier: Programming Language :: Python :: 3.10
Classifier: Programming Language :: Python :: 3.7
Classifier: Programming Language :: Python :: 3.8
Classifier: Programming Language :: Python :: 3.9
Requires-Dist: importlib-metadata (>=4.8,<5.0); python_version < "3.8"
Project-URL: Repository, https://github.com/ninoseki/niteru
